autosubset/__init__.py
autosubset-0.3.0.dist-info/licenses/LICENSE.md
autosubset-0.3.0.dist-info/METADATA
autosubset-0.3.0.dist-info/WHEEL
autosubset-0.3.0.dist-info/entry_points.txt
autosubset-0.3.0.dist-info/top_level.txt
autosubset-0.3.0.dist-info/RECORD
