Metadata-Version: 2.4
Name: autosubset
Version: 0.3.0
Summary: Automatically create an optimized subset font using fonttool's pyftsubset
Home-page: https://gitlab.com/MarcelWaldvogel/autosubset
Author: Marcel Waldvogel
Author-email: marcel.waldvogel@trifence.ch
License: MIT
Classifier: Development Status :: 3 - Alpha
Classifier: Intended Audience :: Information Technology
Classifier: Programming Language :: Python
Classifier: License :: OSI Approved :: MIT License
Classifier: Operating System :: OS Independent
Classifier: Natural Language :: English
Requires-Python: >=3.6
License-File: LICENSE.md
Requires-Dist: fonttools[woff]>2.5
Dynamic: author
Dynamic: author-email
Dynamic: classifier
Dynamic: description
Dynamic: description-content-type
Dynamic: home-page
Dynamic: license
Dynamic: license-file
Dynamic: requires-dist
Dynamic: requires-python
Dynamic: summary
